game_manager/__init__.py
game_manager/samples/__init__.py
game_manager/samples/camera_sample.py
game_manager/samples/sample.py
game_manager/samples/sample_game_array.py
game_manager/samples/graphics/AMBULANCE_CLEAN_ALLD0000-sheet.png
game_manager/samples/graphics/bg.png
game_manager/samples/graphics/ground.png
game_manager/samples/graphics/player.png
game_manager/samples/graphics/tree.png
game_manager/src/__init__.py
game_manager/src/background.py
game_manager/src/cameras.py
game_manager/src/sprite_sheet_array.py
game_manager/utilities/__init__.py
game_manager/utilities/draw.py
game_manager-0.1.dist-info/METADATA
game_manager-0.1.dist-info/WHEEL
game_manager-0.1.dist-info/top_level.txt
game_manager-0.1.dist-info/RECORD
