Metadata-Version: 2.1
Name: game_manager
Version: 0.1
Summary: A brief description of your package
Home-page: https://github.com/mmaleki92/GameMananger
Author: Morteza Maleki
Author-email: maleki.morteza92@gmail.com
Classifier: Programming Language :: Python :: 3
Classifier: License :: OSI Approved :: MIT License
Classifier: Operating System :: OS Independent
Requires-Python: >=3.6
Requires-Dist: numpy
Requires-Dist: natsort
Requires-Dist: pygame
